{
  "properties": {
    "displayName": "NSG rule ports without IP source",
    "policyType": "Custom",
    "mode": "All",
    "metadata": {
      "category": "Network"
    },
    "parameters": {
      "ipAddresses": {
        "type": "Array",
        "metadata": {
          "displayname": "Destination Port Ranges"
        }
      }
    },
    "policyRule": {
      "if": {
        "allOf": [
          {
            "field": "type",
            "equals": "Microsoft.Network/networkSecurityGroups/securityRules"
          },
          {
            "field": "Microsoft.Network/networkSecurityGroups/securityRules/destinationPortRange",
            "in": "[parameters('ipAddresses')]"
          },
          {
            "field": "Microsoft.Network/networkSecurityGroups/securityRules/sourceAddressPrefix",
            "equals": "*"
          },
          {
            "field": "Microsoft.Network/networkSecurityGroups/securityRules/access",
            "equals": "Allow"
          }
        ]
      },
      "then": {
        "effect": "deny"
      }
    }
  }
}